{
  "$schema": "https://zed.dev/schema/icon_themes/v0.2.0.json",
  "name": "Aurora Neon Icons",
  "author": "jmagar",
  "themes": [
    {
      "name": "Aurora Neon Icons",
      "appearance": "dark",
      "directory_icons": {
        "collapsed": "icons/folder.svg",
        "expanded": "icons/folder_open.svg"
      },
      "chevron_icons": {
        "collapsed": "icons/chevron.svg",
        "expanded": "icons/chevron_down.svg"
      },
      "file_stems": {
        "Dockerfile": "docker",
        "docker-compose": "docker",
        "compose": "docker",
        "Makefile": "make",
        "justfile": "config",
        "CMakeLists": "make",
        "package": "config",
        "tsconfig": "config",
        "components": "config",
        ".gitignore": "git",
        ".gitattributes": "git",
        ".gitconfig": "git",
        ".env": "env",
        ".editorconfig": "config",
        ".prettierrc": "config",
        "LICENSE": "license",
        "LICENSE.md": "license",
        "README": "markdown",
        "Cargo": "config",
        "go": "config",
        "flake": "nix",
        "shell": "nix"
      },
      "file_suffixes": {
        "ts": "typescript",
        "mts": "typescript",
        "cts": "typescript",
        "tsx": "react",
        "js": "javascript",
        "mjs": "javascript",
        "cjs": "javascript",
        "jsx": "react",
        "vue": "vue",
        "svelte": "svelte",
        "astro": "astro",
        "html": "html",
        "htm": "html",
        "css": "css",
        "scss": "sass",
        "sass": "sass",
        "less": "sass",
        "graphql": "graphql",
        "gql": "graphql",
        "rs": "rust",
        "go": "go",
        "c": "c",
        "h": "header",
        "hpp": "header",
        "cpp": "cpp",
        "cc": "cpp",
        "cxx": "cpp",
        "zig": "zig",
        "cs": "csharp",
        "swift": "swift",
        "py": "python",
        "pyi": "python",
        "rb": "ruby",
        "sh": "shell",
        "bash": "shell",
        "zsh": "shell",
        "fish": "shell",
        "lua": "lua",
        "pl": "perl",
        "pm": "perl",
        "php": "php",
        "java": "java",
        "kt": "kotlin",
        "kts": "kotlin",
        "scala": "scala",
        "sc": "scala",
        "clj": "clojure",
        "cljs": "clojure",
        "cljc": "clojure",
        "json": "json",
        "jsonc": "json",
        "json5": "json",
        "yaml": "yaml",
        "yml": "yaml",
        "toml": "toml",
        "xml": "xml",
        "csv": "csv",
        "tsv": "csv",
        "sql": "sql",
        "parquet": "data",
        "arrow": "data",
        "md": "markdown",
        "mdx": "markdown",
        "markdown": "markdown",
        "rst": "text",
        "txt": "text",
        "text": "text",
        "adoc": "text",
        "pdf": "pdf",
        "doc": "doc",
        "docx": "doc",
        "epub": "book",
        "env": "env",
        "lock": "lock",
        "nix": "nix",
        "mk": "make",
        "cmake": "make",
        "png": "image",
        "jpg": "image",
        "jpeg": "image",
        "gif": "image",
        "webp": "image",
        "bmp": "image",
        "ico": "image",
        "svg": "svg",
        "mp3": "audio",
        "wav": "audio",
        "flac": "audio",
        "ogg": "audio",
        "mp4": "video",
        "mkv": "video",
        "mov": "video",
        "webm": "video",
        "avi": "video",
        "ttf": "font",
        "otf": "font",
        "woff": "font",
        "woff2": "font"
      },
      "file_icons": {
        "typescript": {
          "path": "icons/typescript.svg"
        },
        "javascript": {
          "path": "icons/javascript.svg"
        },
        "react": {
          "path": "icons/react.svg"
        },
        "vue": {
          "path": "icons/vue.svg"
        },
        "svelte": {
          "path": "icons/svelte.svg"
        },
        "astro": {
          "path": "icons/astro.svg"
        },
        "html": {
          "path": "icons/html.svg"
        },
        "css": {
          "path": "icons/css.svg"
        },
        "sass": {
          "path": "icons/sass.svg"
        },
        "graphql": {
          "path": "icons/graphql.svg"
        },
        "rust": {
          "path": "icons/rust.svg"
        },
        "go": {
          "path": "icons/go.svg"
        },
        "c": {
          "path": "icons/c.svg"
        },
        "cpp": {
          "path": "icons/cpp.svg"
        },
        "header": {
          "path": "icons/header.svg"
        },
        "zig": {
          "path": "icons/zig.svg"
        },
        "csharp": {
          "path": "icons/csharp.svg"
        },
        "swift": {
          "path": "icons/swift.svg"
        },
        "python": {
          "path": "icons/python.svg"
        },
        "ruby": {
          "path": "icons/ruby.svg"
        },
        "shell": {
          "path": "icons/shell.svg"
        },
        "lua": {
          "path": "icons/lua.svg"
        },
        "perl": {
          "path": "icons/perl.svg"
        },
        "php": {
          "path": "icons/php.svg"
        },
        "java": {
          "path": "icons/java.svg"
        },
        "kotlin": {
          "path": "icons/kotlin.svg"
        },
        "scala": {
          "path": "icons/scala.svg"
        },
        "clojure": {
          "path": "icons/clojure.svg"
        },
        "json": {
          "path": "icons/json.svg"
        },
        "yaml": {
          "path": "icons/yaml.svg"
        },
        "toml": {
          "path": "icons/toml.svg"
        },
        "xml": {
          "path": "icons/xml.svg"
        },
        "csv": {
          "path": "icons/csv.svg"
        },
        "sql": {
          "path": "icons/sql.svg"
        },
        "data": {
          "path": "icons/data.svg"
        },
        "markdown": {
          "path": "icons/markdown.svg"
        },
        "text": {
          "path": "icons/text.svg"
        },
        "pdf": {
          "path": "icons/pdf.svg"
        },
        "doc": {
          "path": "icons/doc.svg"
        },
        "license": {
          "path": "icons/license.svg"
        },
        "book": {
          "path": "icons/book.svg"
        },
        "env": {
          "path": "icons/env.svg"
        },
        "lock": {
          "path": "icons/lock.svg"
        },
        "docker": {
          "path": "icons/docker.svg"
        },
        "git": {
          "path": "icons/git.svg"
        },
        "config": {
          "path": "icons/config.svg"
        },
        "settings": {
          "path": "icons/settings.svg"
        },
        "terminal": {
          "path": "icons/terminal.svg"
        },
        "make": {
          "path": "icons/make.svg"
        },
        "nix": {
          "path": "icons/nix.svg"
        },
        "image": {
          "path": "icons/image.svg"
        },
        "audio": {
          "path": "icons/audio.svg"
        },
        "video": {
          "path": "icons/video.svg"
        },
        "font": {
          "path": "icons/font.svg"
        },
        "svg": {
          "path": "icons/svg.svg"
        },
        "default": {
          "path": "icons/default.svg"
        }
      }
    },
    {
      "name": "Aurora Neon Icons Light",
      "appearance": "light",
      "directory_icons": {
        "collapsed": "icons/folder.svg",
        "expanded": "icons/folder_open.svg"
      },
      "chevron_icons": {
        "collapsed": "icons/chevron.svg",
        "expanded": "icons/chevron_down.svg"
      },
      "file_stems": {
        "Dockerfile": "docker",
        "docker-compose": "docker",
        "compose": "docker",
        "Makefile": "make",
        "justfile": "config",
        "CMakeLists": "make",
        "package": "config",
        "tsconfig": "config",
        "components": "config",
        ".gitignore": "git",
        ".gitattributes": "git",
        ".gitconfig": "git",
        ".env": "env",
        ".editorconfig": "config",
        ".prettierrc": "config",
        "LICENSE": "license",
        "LICENSE.md": "license",
        "README": "markdown",
        "Cargo": "config",
        "go": "config",
        "flake": "nix",
        "shell": "nix"
      },
      "file_suffixes": {
        "ts": "typescript",
        "mts": "typescript",
        "cts": "typescript",
        "tsx": "react",
        "js": "javascript",
        "mjs": "javascript",
        "cjs": "javascript",
        "jsx": "react",
        "vue": "vue",
        "svelte": "svelte",
        "astro": "astro",
        "html": "html",
        "htm": "html",
        "css": "css",
        "scss": "sass",
        "sass": "sass",
        "less": "sass",
        "graphql": "graphql",
        "gql": "graphql",
        "rs": "rust",
        "go": "go",
        "c": "c",
        "h": "header",
        "hpp": "header",
        "cpp": "cpp",
        "cc": "cpp",
        "cxx": "cpp",
        "zig": "zig",
        "cs": "csharp",
        "swift": "swift",
        "py": "python",
        "pyi": "python",
        "rb": "ruby",
        "sh": "shell",
        "bash": "shell",
        "zsh": "shell",
        "fish": "shell",
        "lua": "lua",
        "pl": "perl",
        "pm": "perl",
        "php": "php",
        "java": "java",
        "kt": "kotlin",
        "kts": "kotlin",
        "scala": "scala",
        "sc": "scala",
        "clj": "clojure",
        "cljs": "clojure",
        "cljc": "clojure",
        "json": "json",
        "jsonc": "json",
        "json5": "json",
        "yaml": "yaml",
        "yml": "yaml",
        "toml": "toml",
        "xml": "xml",
        "csv": "csv",
        "tsv": "csv",
        "sql": "sql",
        "parquet": "data",
        "arrow": "data",
        "md": "markdown",
        "mdx": "markdown",
        "markdown": "markdown",
        "rst": "text",
        "txt": "text",
        "text": "text",
        "adoc": "text",
        "pdf": "pdf",
        "doc": "doc",
        "docx": "doc",
        "epub": "book",
        "env": "env",
        "lock": "lock",
        "nix": "nix",
        "mk": "make",
        "cmake": "make",
        "png": "image",
        "jpg": "image",
        "jpeg": "image",
        "gif": "image",
        "webp": "image",
        "bmp": "image",
        "ico": "image",
        "svg": "svg",
        "mp3": "audio",
        "wav": "audio",
        "flac": "audio",
        "ogg": "audio",
        "mp4": "video",
        "mkv": "video",
        "mov": "video",
        "webm": "video",
        "avi": "video",
        "ttf": "font",
        "otf": "font",
        "woff": "font",
        "woff2": "font"
      },
      "file_icons": {
        "typescript": {
          "path": "icons/typescript.svg"
        },
        "javascript": {
          "path": "icons/javascript.svg"
        },
        "react": {
          "path": "icons/react.svg"
        },
        "vue": {
          "path": "icons/vue.svg"
        },
        "svelte": {
          "path": "icons/svelte.svg"
        },
        "astro": {
          "path": "icons/astro.svg"
        },
        "html": {
          "path": "icons/html.svg"
        },
        "css": {
          "path": "icons/css.svg"
        },
        "sass": {
          "path": "icons/sass.svg"
        },
        "graphql": {
          "path": "icons/graphql.svg"
        },
        "rust": {
          "path": "icons/rust.svg"
        },
        "go": {
          "path": "icons/go.svg"
        },
        "c": {
          "path": "icons/c.svg"
        },
        "cpp": {
          "path": "icons/cpp.svg"
        },
        "header": {
          "path": "icons/header.svg"
        },
        "zig": {
          "path": "icons/zig.svg"
        },
        "csharp": {
          "path": "icons/csharp.svg"
        },
        "swift": {
          "path": "icons/swift.svg"
        },
        "python": {
          "path": "icons/python.svg"
        },
        "ruby": {
          "path": "icons/ruby.svg"
        },
        "shell": {
          "path": "icons/shell.svg"
        },
        "lua": {
          "path": "icons/lua.svg"
        },
        "perl": {
          "path": "icons/perl.svg"
        },
        "php": {
          "path": "icons/php.svg"
        },
        "java": {
          "path": "icons/java.svg"
        },
        "kotlin": {
          "path": "icons/kotlin.svg"
        },
        "scala": {
          "path": "icons/scala.svg"
        },
        "clojure": {
          "path": "icons/clojure.svg"
        },
        "json": {
          "path": "icons/json.svg"
        },
        "yaml": {
          "path": "icons/yaml.svg"
        },
        "toml": {
          "path": "icons/toml.svg"
        },
        "xml": {
          "path": "icons/xml.svg"
        },
        "csv": {
          "path": "icons/csv.svg"
        },
        "sql": {
          "path": "icons/sql.svg"
        },
        "data": {
          "path": "icons/data.svg"
        },
        "markdown": {
          "path": "icons/markdown.svg"
        },
        "text": {
          "path": "icons/text.svg"
        },
        "pdf": {
          "path": "icons/pdf.svg"
        },
        "doc": {
          "path": "icons/doc.svg"
        },
        "license": {
          "path": "icons/license.svg"
        },
        "book": {
          "path": "icons/book.svg"
        },
        "env": {
          "path": "icons/env.svg"
        },
        "lock": {
          "path": "icons/lock.svg"
        },
        "docker": {
          "path": "icons/docker.svg"
        },
        "git": {
          "path": "icons/git.svg"
        },
        "config": {
          "path": "icons/config.svg"
        },
        "settings": {
          "path": "icons/settings.svg"
        },
        "terminal": {
          "path": "icons/terminal.svg"
        },
        "make": {
          "path": "icons/make.svg"
        },
        "nix": {
          "path": "icons/nix.svg"
        },
        "image": {
          "path": "icons/image.svg"
        },
        "audio": {
          "path": "icons/audio.svg"
        },
        "video": {
          "path": "icons/video.svg"
        },
        "font": {
          "path": "icons/font.svg"
        },
        "svg": {
          "path": "icons/svg.svg"
        },
        "default": {
          "path": "icons/default.svg"
        }
      }
    }
  ]
}
