{
  "$schema": "https://ui.shadcn.com/schema/registry-item.json",
  "name": "aurora-web-preview",
  "title": "Aurora Web Preview",
  "author": "jmagar <https://github.com/jmagar>",
  "description": "Browser chrome component with Aurora panel titlebar, three neutral square window dots, address bar with lock icon, reload and share icon buttons. Four variants: browser (full chrome), unfurl-card (link preview with favicon, title, description, domain chip), skeleton (shimmer loading), and error (failed to load).",
  "dependencies": [
    "lucide-react@^1.21.0"
  ],
  "registryDependencies": [
    "@aurora/aurora-tokens",
    "@aurora/aurora-button",
    "@aurora/aurora-components"
  ],
  "files": [
    {
      "path": "registry/aurora/blocks/workspace/web-preview/web-preview.tsx",
      "content": "\"use client\"\n\nimport * as React from \"react\"\nimport {\n  CircleAlert,\n  ExternalLink,\n  Globe2,\n  Lock,\n  Monitor,\n  RefreshCw,\n  Smartphone,\n  Tablet,\n} from \"lucide-react\"\nimport { Button } from \"@/registry/aurora/ui/button\"\n\n// ---------------------------------------------------------------------------\n// Types\n// ---------------------------------------------------------------------------\n\nexport type WebPreviewVariant = \"browser\" | \"unfurl-card\" | \"skeleton\" | \"error\"\nexport type WebPreviewViewport = \"desktop\" | \"tablet\" | \"mobile\"\n\nexport interface WebPreviewProps {\n  url: string\n  title?: string\n  description?: string\n  favicon?: string\n  screenshot?: string\n  variant?: WebPreviewVariant\n  isLoading?: boolean\n  /** Show viewport toggle buttons in the browser chrome (default: true) */\n  showViewportToggle?: boolean\n  /** Show the Console strip at the bottom (default: true) */\n  showConsole?: boolean\n  /** Number shown in the Console badge */\n  consoleCount?: number\n}\n\n// ---------------------------------------------------------------------------\n// Icons\n// ---------------------------------------------------------------------------\n\nconst ICON_STROKE = 1.65\n\nfunction ReloadIcon() {\n  return <RefreshCw size={14} strokeWidth={ICON_STROKE} aria-hidden />\n}\n\n\nfunction LockIcon() {\n  return <Lock size={12} strokeWidth={ICON_STROKE} aria-hidden />\n}\n\nfunction GlobeIcon() {\n  return <Globe2 size={16} strokeWidth={ICON_STROKE} aria-hidden />\n}\n\nfunction DesktopIcon() {\n  return <Monitor size={16} strokeWidth={ICON_STROKE} aria-hidden />\n}\n\nfunction TabletIcon() {\n  return <Tablet size={16} strokeWidth={ICON_STROKE} aria-hidden />\n}\n\nfunction MobileIcon() {\n  return <Smartphone size={16} strokeWidth={ICON_STROKE} aria-hidden />\n}\n\nfunction ExternalLinkIcon() {\n  return <ExternalLink size={14} strokeWidth={ICON_STROKE} aria-hidden />\n}\n\nfunction AlertIcon() {\n  return <CircleAlert size={32} strokeWidth={1.75} aria-hidden style={{ color: \"var(--aurora-error)\" }} />\n}\n\n// ---------------------------------------------------------------------------\n// Window dots (three neutral squares — NOT Mac colored)\n// ---------------------------------------------------------------------------\n\nfunction WindowDots() {\n  return (\n    <div style={{ display: \"flex\", gap: \"5px\", alignItems: \"center\" }}>\n      {[0, 1, 2].map((i) => (\n        <span\n          key={i}\n          style={{\n            display: \"inline-block\",\n            width: \"10px\",\n            height: \"10px\",\n            borderRadius: \"2px\",\n            background: \"var(--aurora-border-strong)\",\n          }}\n        />\n      ))}\n    </div>\n  )\n}\n\n// ---------------------------------------------------------------------------\n// Chrome button\n// ---------------------------------------------------------------------------\n\nfunction ChromeButton({\n  children,\n  onClick,\n  title,\n}: {\n  children: React.ReactNode\n  onClick?: () => void\n  title?: string\n}) {\n  return (\n    <Button\n      type=\"button\"\n      variant=\"ghost\"\n      size=\"icon\"\n      onClick={onClick}\n      title={title}\n      aria-label={title}\n      style={{\n        width: \"28px\",\n        height: \"26px\",\n        padding: 0,\n      }}\n    >\n      {children}\n    </Button>\n  )\n}\n\n// ---------------------------------------------------------------------------\n// Skeleton shimmer\n// ---------------------------------------------------------------------------\n\n// Styles: registry/aurora/styles/aurora-components.css (@layer aurora-components).\n\nfunction SkeletonBlock({ width = \"100%\", height = \"14px\", style }: { width?: string; height?: string; style?: React.CSSProperties }) {\n  return (\n    <div\n      className=\"aurora-shimmer-block\"\n      style={{ width, height, borderRadius: \"6px\", ...style }}\n    />\n  )\n}\n\n// ---------------------------------------------------------------------------\n// URL parser helper\n// ---------------------------------------------------------------------------\n\nfunction getDomain(url: string): string {\n  try {\n    return new URL(url).hostname\n  } catch {\n    return url\n  }\n}\n\nfunction isHttps(url: string): boolean {\n  return url.startsWith(\"https://\")\n}\n\n// ---------------------------------------------------------------------------\n// Variants\n// ---------------------------------------------------------------------------\n\nfunction BrowserChrome({\n  url,\n  title,\n  screenshot,\n  isLoading,\n  showViewportToggle = true,\n  showConsole = true,\n  consoleCount = 3,\n}: WebPreviewProps) {\n  const domain = getDomain(url)\n  const secure = isHttps(url)\n  const [viewport, setViewport] = React.useState<WebPreviewViewport>(\"desktop\")\n  const [consoleOpen, setConsoleOpen] = React.useState(false)\n\n  const VIEWPORTS: { id: WebPreviewViewport; Icon: () => React.ReactElement; label: string }[] = [\n    { id: \"desktop\", Icon: DesktopIcon, label: \"Desktop\" },\n    { id: \"tablet\",  Icon: TabletIcon,  label: \"Tablet\" },\n    { id: \"mobile\",  Icon: MobileIcon,  label: \"Mobile\" },\n  ]\n\n  return (\n    <div\n      style={{\n        display: \"flex\",\n        flexDirection: \"column\",\n        border: \"1px solid var(--aurora-border-default)\",\n        borderRadius: \"var(--aurora-radius-2)\",\n        overflow: \"hidden\",\n        boxShadow: \"var(--aurora-shadow-medium)\",\n      }}\n    >\n      {/* Titlebar */}\n      <div\n        style={{\n          display: \"flex\",\n          alignItems: \"center\",\n          gap: \"10px\",\n          padding: \"0 12px\",\n          height: \"42px\",\n          background: \"var(--aurora-panel-strong)\",\n          borderBottom: \"1px solid var(--aurora-border-default)\",\n          flexShrink: 0,\n        }}\n      >\n        <ChromeButton title=\"Reload\"><ReloadIcon /></ChromeButton>\n        {/* Address bar */}\n        <div\n          style={{\n            flex: 1,\n            display: \"flex\",\n            alignItems: \"center\",\n            gap: \"6px\",\n            height: \"28px\",\n            padding: \"0 10px\",\n            background: \"var(--aurora-control-surface)\",\n            border: \"1px solid var(--aurora-border-default)\",\n            borderRadius: \"8px\",\n            fontFamily: \"var(--aurora-font-sans)\",\n            fontSize: \"12px\",\n            color: \"var(--aurora-text-muted)\",\n            overflow: \"hidden\",\n          }}\n        >\n          <span style={{ color: secure ? \"var(--aurora-success)\" : \"var(--aurora-warn)\", flexShrink: 0 }}>\n            <LockIcon />\n          </span>\n          <span\n            style={{\n              overflow: \"hidden\",\n              textOverflow: \"ellipsis\",\n              whiteSpace: \"nowrap\",\n              flex: 1,\n            }}\n          >\n            {url}\n          </span>\n          {/* Live indicator dot */}\n          <span\n            style={{\n              width: \"7px\",\n              height: \"7px\",\n              borderRadius: \"50%\",\n              background: \"var(--aurora-success)\",\n              flexShrink: 0,\n            }}\n          />\n        </div>\n        {/* Viewport toggles */}\n        {showViewportToggle && (\n          <div style={{ display: \"flex\", gap: \"2px\" }}>\n            {VIEWPORTS.map(({ id, Icon, label }) => {\n              const active = viewport === id\n              return (\n                <Button\n                  variant=\"plain\"\n                  size=\"unstyled\"\n                  key={id}\n                  type=\"button\"\n                  aria-label={label}\n                  title={label}\n                  onClick={() => setViewport(id)}\n                  style={{\n                    display: \"inline-flex\",\n                    alignItems: \"center\",\n                    justifyContent: \"center\",\n                    width: \"28px\",\n                    height: \"26px\",\n                    border: active ? \"1px solid color-mix(in srgb, var(--aurora-accent-primary) 40%, transparent)\" : \"1px solid transparent\",\n                    borderRadius: \"6px\",\n                    background: active ? \"color-mix(in srgb, var(--aurora-accent-primary) 12%, transparent)\" : \"transparent\",\n                    color: active ? \"var(--aurora-accent-primary)\" : \"var(--aurora-text-muted)\",\n                    cursor: \"pointer\",\n                    padding: 0,\n                  }}\n                >\n                  <Icon />\n                </Button>\n              )\n            })}\n          </div>\n        )}\n        <ChromeButton title=\"Open in new tab\"><ExternalLinkIcon /></ChromeButton>\n      </div>\n\n      {/* Content area */}\n      <div\n        style={{\n          background: \"var(--aurora-panel-medium)\",\n          minHeight: \"200px\",\n          display: \"flex\",\n          alignItems: \"center\",\n          justifyContent: \"center\",\n          position: \"relative\",\n          overflow: \"hidden\",\n        }}\n      >\n        {isLoading ? (\n          <div style={{ width: \"100%\", padding: \"24px\", display: \"flex\", flexDirection: \"column\", gap: \"10px\" }}>\n            <SkeletonBlock height=\"20px\" width=\"60%\" />\n            <SkeletonBlock height=\"14px\" width=\"90%\" />\n            <SkeletonBlock height=\"14px\" width=\"75%\" />\n            <SkeletonBlock height=\"14px\" width=\"50%\" />\n          </div>\n        ) : screenshot ? (\n          <img\n            src={screenshot}\n            alt={title ?? domain}\n            style={{ width: \"100%\", height: \"100%\", objectFit: \"cover\", display: \"block\" }}\n          />\n        ) : (\n          <div style={{ textAlign: \"center\", padding: \"32px\" }}>\n            <GlobeIcon />\n            <div\n              style={{\n                marginTop: \"10px\",\n                fontFamily: \"var(--aurora-font-sans)\",\n                fontSize: \"13px\",\n                color: \"var(--aurora-text-muted)\",\n              }}\n            >\n              {title ?? domain}\n            </div>\n          </div>\n        )}\n      </div>\n\n      {/* Console strip */}\n      {showConsole && (\n        <div\n          style={{\n            borderTop: \"1px solid var(--aurora-border-default)\",\n            background: \"var(--aurora-panel-strong)\",\n          }}\n        >\n          <Button\n            variant=\"plain\"\n            size=\"unstyled\"\n            type=\"button\"\n            onClick={() => setConsoleOpen((o) => !o)}\n            style={{\n              display: \"flex\",\n              alignItems: \"center\",\n              gap: \"8px\",\n              width: \"100%\",\n              padding: \"0 12px\",\n              height: \"32px\",\n              background: \"transparent\",\n              border: \"none\",\n              cursor: \"pointer\",\n              color: \"var(--aurora-text-muted)\",\n              fontFamily: \"var(--aurora-font-sans)\",\n              fontSize: \"12px\",\n              textAlign: \"left\",\n            }}\n          >\n            <span style={{ fontSize: \"10px\", opacity: 0.7 }}>{consoleOpen ? \"▾\" : \"▸\"}</span>\n            <span>Console</span>\n            {consoleCount > 0 && (\n              <span\n                style={{\n                  display: \"inline-flex\",\n                  alignItems: \"center\",\n                  justifyContent: \"center\",\n                  minWidth: \"18px\",\n                  height: \"16px\",\n                  padding: \"0 5px\",\n                  borderRadius: \"10px\",\n                  background: \"color-mix(in srgb, var(--aurora-warn) 18%, transparent)\",\n                  color: \"var(--aurora-warn)\",\n                  fontFamily: \"var(--aurora-font-sans)\",\n                  fontVariantNumeric: \"tabular-nums\",\n                  fontSize: \"10px\",\n                  fontWeight: 600,\n                }}\n              >\n                {consoleCount}\n              </span>\n            )}\n          </Button>\n          {consoleOpen && (\n            <div\n              style={{\n                padding: \"8px 12px\",\n                borderTop: \"1px solid var(--aurora-border-default)\",\n                fontFamily: \"var(--aurora-font-mono)\",\n                fontSize: \"11px\",\n                color: \"var(--aurora-text-muted)\",\n                display: \"flex\",\n                flexDirection: \"column\",\n                gap: \"4px\",\n              }}\n            >\n              <span style={{ color: \"var(--aurora-warn)\" }}>⚠ Mixed content blocked (2)</span>\n              <span style={{ color: \"var(--aurora-text-muted)\" }}>&gt; Labby gateway connected</span>\n            </div>\n          )}\n        </div>\n      )}\n    </div>\n  )\n}\n\nfunction UnfurlCard({ url, title, description, favicon }: WebPreviewProps) {\n  const domain = getDomain(url)\n  const [hovered, setHovered] = React.useState(false)\n\n  return (\n    <a\n      href={url}\n      target=\"_blank\"\n      rel=\"noopener noreferrer\"\n      onMouseEnter={() => setHovered(true)}\n      onMouseLeave={() => setHovered(false)}\n      style={{\n        display: \"flex\",\n        alignItems: \"stretch\",\n        gap: 0,\n        textDecoration: \"none\",\n        border: `1px solid ${hovered ? \"var(--aurora-border-strong)\" : \"var(--aurora-border-default)\"}`,\n        borderRadius: \"var(--aurora-radius-1)\",\n        background: \"var(--aurora-panel-strong)\",\n        overflow: \"hidden\",\n        boxShadow: hovered ? \"var(--aurora-shadow-medium)\" : \"none\",\n        transition: \"border-color 0.15s, box-shadow 0.15s\",\n        maxWidth: \"480px\",\n      }}\n    >\n      {/* Accent bar */}\n      <div\n        style={{\n          width: \"3px\",\n          background: \"var(--aurora-accent-primary)\",\n          flexShrink: 0,\n          opacity: 0.7,\n        }}\n      />\n      <div style={{ padding: \"12px 14px\", flex: 1, minWidth: 0 }}>\n        {/* Domain chip */}\n        <div style={{ display: \"flex\", alignItems: \"center\", gap: \"6px\", marginBottom: \"6px\" }}>\n          {favicon ? (\n            <img src={favicon} alt=\"\" width=\"14\" height=\"14\" style={{ borderRadius: \"3px\", flexShrink: 0 }} />\n          ) : (\n            <span style={{ color: \"var(--aurora-text-muted)\", flexShrink: 0 }}>\n              <GlobeIcon />\n            </span>\n          )}\n          <span\n            style={{\n              fontFamily: \"var(--aurora-font-sans)\",\n              fontSize: \"11px\",\n              color: \"var(--aurora-text-muted)\",\n              overflow: \"hidden\",\n              textOverflow: \"ellipsis\",\n              whiteSpace: \"nowrap\",\n            }}\n          >\n            {domain}\n          </span>\n        </div>\n\n        {title && (\n          <div\n            style={{\n              fontFamily: \"var(--aurora-font-sans)\",\n              fontSize: \"14px\",\n              fontWeight: 600,\n              color: \"var(--aurora-text-primary)\",\n              marginBottom: \"4px\",\n              overflow: \"hidden\",\n              textOverflow: \"ellipsis\",\n              whiteSpace: \"nowrap\",\n            }}\n          >\n            {title}\n          </div>\n        )}\n\n        {description && (\n          <div\n            style={{\n              fontFamily: \"var(--aurora-font-sans)\",\n              fontSize: \"12px\",\n              color: \"var(--aurora-text-muted)\",\n              display: \"-webkit-box\",\n              WebkitLineClamp: 2,\n              WebkitBoxOrient: \"vertical\",\n              overflow: \"hidden\",\n              lineHeight: 1.45,\n            }}\n          >\n            {description}\n          </div>\n        )}\n      </div>\n    </a>\n  )\n}\n\nfunction SkeletonVariant({ url }: { url: string }) {\n  void url\n  return (\n    <div\n      style={{\n        border: \"1px solid var(--aurora-border-default)\",\n        borderRadius: \"var(--aurora-radius-2)\",\n        overflow: \"hidden\",\n        boxShadow: \"var(--aurora-shadow-medium)\",\n      }}\n    >\n      {/* Skeleton titlebar */}\n      <div\n        style={{\n          display: \"flex\",\n          alignItems: \"center\",\n          gap: \"10px\",\n          padding: \"0 12px\",\n          height: \"42px\",\n          background: \"var(--aurora-panel-strong)\",\n          borderBottom: \"1px solid var(--aurora-border-default)\",\n        }}\n      >\n        <WindowDots />\n        <SkeletonBlock height=\"26px\" style={{ flex: 1, borderRadius: \"8px\" }} />\n      </div>\n      {/* Skeleton body */}\n      <div\n        style={{\n          background: \"var(--aurora-panel-medium)\",\n          padding: \"24px\",\n          display: \"flex\",\n          flexDirection: \"column\",\n          gap: \"10px\",\n          minHeight: \"140px\",\n        }}\n      >\n        <SkeletonBlock height=\"18px\" width=\"55%\" />\n        <SkeletonBlock height=\"13px\" width=\"85%\" />\n        <SkeletonBlock height=\"13px\" width=\"70%\" />\n        <SkeletonBlock height=\"13px\" width=\"40%\" />\n      </div>\n    </div>\n  )\n}\n\nfunction ErrorVariant({ url }: { url: string }) {\n  const domain = getDomain(url)\n  return (\n    <div\n      style={{\n        border: \"1px solid var(--aurora-border-default)\",\n        borderRadius: \"var(--aurora-radius-2)\",\n        overflow: \"hidden\",\n        boxShadow: \"var(--aurora-shadow-medium)\",\n      }}\n    >\n      {/* Titlebar */}\n      <div\n        style={{\n          display: \"flex\",\n          alignItems: \"center\",\n          gap: \"10px\",\n          padding: \"0 12px\",\n          height: \"42px\",\n          background: \"var(--aurora-panel-strong)\",\n          borderBottom: \"1px solid var(--aurora-border-default)\",\n        }}\n      >\n        <WindowDots />\n        <div\n          style={{\n            flex: 1,\n            height: \"26px\",\n            display: \"flex\",\n            alignItems: \"center\",\n            padding: \"0 10px\",\n            background: \"var(--aurora-control-surface)\",\n            border: \"1px solid var(--aurora-border-default)\",\n            borderRadius: \"8px\",\n            fontFamily: \"var(--aurora-font-sans)\",\n            fontSize: \"12px\",\n            color: \"var(--aurora-text-muted)\",\n            overflow: \"hidden\",\n          }}\n        >\n          <span\n            style={{\n              overflow: \"hidden\",\n              textOverflow: \"ellipsis\",\n              whiteSpace: \"nowrap\",\n            }}\n          >\n            {url}\n          </span>\n        </div>\n        <ChromeButton title=\"Reload\"><ReloadIcon /></ChromeButton>\n      </div>\n\n      {/* Error body */}\n      <div\n        style={{\n          background: \"color-mix(in srgb, var(--aurora-error) 4%, var(--aurora-panel-medium))\",\n          minHeight: \"160px\",\n          display: \"flex\",\n          flexDirection: \"column\",\n          alignItems: \"center\",\n          justifyContent: \"center\",\n          gap: \"12px\",\n          padding: \"32px\",\n        }}\n      >\n        <AlertIcon />\n        <div\n          style={{\n            fontFamily: \"var(--aurora-font-sans)\",\n            fontSize: \"15px\",\n            fontWeight: 600,\n            color: \"var(--aurora-text-primary)\",\n          }}\n        >\n          Failed to load\n        </div>\n        <div\n          style={{\n            fontFamily: \"var(--aurora-font-sans)\",\n            fontSize: \"13px\",\n            color: \"var(--aurora-text-muted)\",\n            textAlign: \"center\",\n          }}\n        >\n          {domain} could not be reached.\n        </div>\n      </div>\n    </div>\n  )\n}\n\n// ---------------------------------------------------------------------------\n// Main WebPreview component\n// ---------------------------------------------------------------------------\n\nexport const WebPreview = React.forwardRef<HTMLDivElement, WebPreviewProps>(\n  function WebPreview(props, ref) {\n    const { variant = \"browser\", isLoading } = props\n\n    const content =\n      isLoading && variant === \"browser\" ? (\n        <BrowserChrome {...props} isLoading />\n      ) : variant === \"skeleton\" ? (\n        <SkeletonVariant {...props} />\n      ) : variant === \"error\" ? (\n        <ErrorVariant {...props} />\n      ) : variant === \"unfurl-card\" ? (\n        <UnfurlCard {...props} />\n      ) : (\n        <BrowserChrome {...props} />\n      )\n\n    return (\n      <div ref={ref} style={{ fontFamily: \"var(--aurora-font-sans)\" }}>\n        {content}\n      </div>\n    )\n  }\n)\n\nexport default WebPreview\n",
      "type": "registry:component",
      "target": "@components/aurora/web-preview.tsx"
    }
  ],
  "meta": {
    "namespace": "@aurora",
    "style": "aurora",
    "family": "block",
    "requiresTokens": true,
    "sourcePath": "registry/aurora/blocks/workspace/web-preview/web-preview.tsx",
    "installTarget": "@components/aurora/web-preview.tsx",
    "taxonomy": "workspace"
  },
  "docs": "Aurora block that installs Aurora Web Preview.\n\nInstall `aurora-tokens`, `aurora-button`, and `aurora-components` first; the shadcn CLI resolves these automatically through the @aurora registry namespace.\n\nDefault install target: `@components/aurora/web-preview.tsx`.\n\nRegistry dependencies: `aurora-tokens`, `aurora-button`, `aurora-components`.",
  "categories": [
    "aurora",
    "block",
    "data-display"
  ],
  "type": "registry:block"
}