{
  "$schema": "https://ui.shadcn.com/schema/registry-item.json",
  "name": "aurora-checkbox",
  "title": "Aurora Checkbox & Radio",
  "author": "jmagar <https://github.com/jmagar>",
  "description": "Aurora-styled checkbox and radio group built on button[role=checkbox/radio] patterns. 16px control with accent-primary fill, animated check/dot, focus ring glow, and full keyboard support. Includes RadioGroup + RadioGroupItem exports.",
  "dependencies": [],
  "registryDependencies": [
    "@aurora/aurora-tokens",
    "@aurora/aurora-button",
    "@aurora/aurora-input",
    "@aurora/aurora-radio-group",
    "@aurora/aurora-select",
    "@aurora/aurora-components"
  ],
  "files": [
    {
      "path": "registry/aurora/ui/checkbox.tsx",
      "content": "\"use client\"\n\nimport * as React from \"react\"\nimport { cn } from \"@/lib/utils\"\n\n// Styles: registry/aurora/styles/aurora-components.css (@layer aurora-components).\n\n// ---------------------------------------------------------------------------\n// Checkbox\n// ---------------------------------------------------------------------------\n\nexport interface CheckboxProps\n  extends Omit<React.ButtonHTMLAttributes<HTMLButtonElement>, \"onChange\"> {\n  checked?: boolean\n  defaultChecked?: boolean\n  /** Tri-state: render a dash instead of a tick (e.g. a partially-selected group). Visually overrides `checked`. */\n  indeterminate?: boolean\n  onCheckedChange?: (checked: boolean) => void\n  /** Label content rendered next to the box. */\n  children?: React.ReactNode\n}\n\nfunction Checkbox({\n  ref,\n  checked,\n  defaultChecked = false,\n  indeterminate = false,\n  onCheckedChange,\n  children,\n  className,\n  disabled,\n  onClick,\n  id,\n  ...props\n}: CheckboxProps & { ref?: React.Ref<HTMLButtonElement> }) {\n  const isControlled = checked !== undefined\n  const [internal, setInternal] = React.useState(defaultChecked)\n  const on = isControlled ? checked : internal\n  const state = indeterminate ? \"indeterminate\" : on ? \"checked\" : \"unchecked\"\n\n  function handleClick(e: React.MouseEvent<HTMLButtonElement>) {\n    if (!isControlled) setInternal((v) => !v)\n    onCheckedChange?.(!on)\n    onClick?.(e)\n  }\n\n  const box = (\n    <button\n      ref={ref}\n      id={children ? undefined : id}\n      type=\"button\"\n      role=\"checkbox\"\n      aria-checked={indeterminate ? \"mixed\" : on}\n      data-state={state}\n      disabled={disabled}\n      className={cn(\"aurora-checkbox\", !children && className)}\n      onClick={handleClick}\n      {...(children ? {} : props)}\n    >\n      {/* Checkmark */}\n      <svg\n        className=\"aurora-checkbox__check\"\n        width=\"13\" height=\"13\" viewBox=\"0 0 24 24\"\n        fill=\"none\" stroke=\"currentColor\" strokeWidth=\"2.4\"\n        strokeLinecap=\"round\" strokeLinejoin=\"round\"\n        aria-hidden=\"true\"\n      >\n        <path d=\"M20 6 9 17l-5-5\" />\n      </svg>\n      {/* Dash (indeterminate) */}\n      <svg\n        className=\"aurora-checkbox__dash\"\n        width=\"13\" height=\"13\" viewBox=\"0 0 24 24\"\n        fill=\"none\" stroke=\"currentColor\" strokeWidth=\"2.4\"\n        strokeLinecap=\"round\"\n        aria-hidden=\"true\"\n      >\n        <path d=\"M6 12h12\" />\n      </svg>\n    </button>\n  )\n\n  if (!children) return box\n\n  return (\n    <label\n      htmlFor={id}\n      className={cn(\n        \"inline-flex items-center gap-[10px]\",\n        disabled ? \"cursor-not-allowed\" : \"cursor-pointer\",\n        className,\n      )}\n    >\n      {box}\n      <span\n        style={{\n          color: disabled ? \"var(--aurora-text-muted)\" : \"var(--aurora-text-primary)\",\n          fontFamily: \"var(--aurora-font-sans)\",\n          fontSize: \"var(--aurora-type-control)\",\n          fontWeight: \"var(--aurora-weight-body)\",\n          letterSpacing: \"var(--aurora-letter-ui)\",\n          lineHeight: \"var(--aurora-line-ui)\",\n          userSelect: \"none\",\n        }}\n      >\n        {children}\n      </span>\n    </label>\n  )\n}\n\n// ---------------------------------------------------------------------------\n// Exports\n// ---------------------------------------------------------------------------\n\nexport { Checkbox }\nexport default Checkbox\n",
      "type": "registry:ui",
      "target": "@ui/aurora/checkbox.tsx"
    }
  ],
  "meta": {
    "namespace": "@aurora",
    "style": "aurora",
    "family": "ui",
    "requiresTokens": true,
    "sourcePath": "registry/aurora/ui/checkbox.tsx",
    "installTarget": "@ui/aurora/checkbox.tsx"
  },
  "docs": "Aurora UI component that installs Aurora Checkbox & Radio.\n\nInstall `aurora-tokens`, `aurora-button`, `aurora-input`, `aurora-radio-group`, `aurora-select`, and `aurora-components` first; the shadcn CLI resolves these automatically through the @aurora registry namespace.\n\nDefault install target: `@ui/aurora/checkbox.tsx`.\n\nRegistry dependencies: `aurora-tokens`, `aurora-button`, `aurora-input`, `aurora-radio-group`, `aurora-select`, `aurora-components`.",
  "categories": [
    "aurora",
    "ui",
    "forms"
  ],
  "type": "registry:ui"
}